{
    "keep": {
        "days": true,
        "amount": 14
    },
    "auditLog": "logs/.8af5475ad9f0797cd70c1ba20edd7c4d91d206da-audit.json",
    "files": [
        {
            "date": 1573492595541,
            "name": "logs/application-2019-11-11.log",
            "hash": "b4075c4a31608ed9d34f27c30b69d6f2"
        },
        {
            "date": 1574145275193,
            "name": "logs\\application-2019-11-19.log",
            "hash": "e2cdac92cb9ce758c262556dd1032add"
        },
        {
            "date": 1574223386597,
            "name": "logs\\application-2019-11-20.log",
            "hash": "f68c24a01bccadd0561bec0312087df8"
        },
        {
            "date": 1574332806276,
            "name": "logs\\application-2019-11-21.log",
            "hash": "2f0cf33b0df4f823df8285e2496e6534"
        },
        {
            "date": 1574397289437,
            "name": "logs\\application-2019-11-22.log",
            "hash": "9078eb0be498b5e3bb74f971a05f1b92"
        },
        {
            "date": 1574585182704,
            "name": "logs/application-2019-11-24.log",
            "hash": "fc16d9e3006010986e3284ffb95f4054"
        }
    ]
}